auth_plus/__forms__test__.py
auth_plus/__init__.py
auth_plus/admin.py
auth_plus/apps.py
auth_plus/backends.py
auth_plus/base.py
auth_plus/constants.py
auth_plus/context_processors.py
auth_plus/converters.py
auth_plus/debug.py
auth_plus/decorators.py
auth_plus/forms.py
auth_plus/middleware.py
auth_plus/mixins.py
auth_plus/shortcuts.py
auth_plus/tests.py
auth_plus/tfa_ways.py
auth_plus/urls.py
auth_plus/utils.py
auth_plus/locale/en/LC_MESSAGES/django.mo
auth_plus/locale/en/LC_MESSAGES/django.po
auth_plus/locale/ru/LC_MESSAGES/django.mo
auth_plus/locale/ru/LC_MESSAGES/django.po
auth_plus/management/__init__.py
auth_plus/management/base.py
auth_plus/management/commands/__init__.py
auth_plus/management/commands/passwordresetdebug.py
auth_plus/migrations/0001_initial.py
auth_plus/migrations/0002_alter_confirmationcode_managers.py
auth_plus/migrations/0003_userotp.py
auth_plus/migrations/0004_alter_user_avatar_alter_user_birth_date_and_more.py
auth_plus/migrations/__init__.py
auth_plus/models/__init__.py
auth_plus/models/base.py
auth_plus/models/generators.py
auth_plus/models/managers.py
auth_plus/models/mixins.py
auth_plus/models/otp.py
auth_plus/models/validators.py
auth_plus/templates/auth_plus/verify_email_complete.html
auth_plus/templates/auth_plus/email/email_base.html
auth_plus/templates/auth_plus/email/email_reset.html
auth_plus/templates/auth_plus/email/email_verification.html
auth_plus/templates/auth_plus/email/email_verify_code_base.html
auth_plus/templates/auth_plus/email/two-factor-auth.html
auth_plus/templates/auth_plus/includes/recaptcha.html
auth_plus/templates/auth_plus/includes/tfa_ways.html
auth_plus/templates/auth_plus/password_reset/password_reset_complete.html
auth_plus/templates/auth_plus/password_reset/password_reset_confirm.html
auth_plus/templates/auth_plus/password_reset/password_reset_done.html
auth_plus/templates/auth_plus/password_reset/password_reset_form.html
hrendjango_auth_plus-0.1.0.dist-info/METADATA
hrendjango_auth_plus-0.1.0.dist-info/WHEEL
hrendjango_auth_plus-0.1.0.dist-info/top_level.txt
hrendjango_auth_plus-0.1.0.dist-info/RECORD
